{
  "url": "https://www.azadvertizer.net/azpolicyadvertizer/fea83f6c-a18a-4338-8f1f-80ecba4c5643.html",
  "timestamp": "2025-06-24T12:38:31.526129",
  "original_policy": {
    "display_name": "Enable logging by category group for Backup vaults (microsoft.dataprotection/backupvaults) to Log Analytics",
    "policy_type": "BuiltIn",
    "had_category_group": true,
    "original_parameters": [
      "effect",
      "diagnosticSettingName",
      "categoryGroup",
      "resourceLocationList",
      "logAnalytics",
      "logAnalyticsDestinationType",
      "collectMetrics"
    ]
  },
  "modified_policy": {
    "service_name_extracted": "Backup vaults",
    "filename_generated": "Backup vaults - custom.json",
    "final_parameters": [
      "effect",
      "diagnosticSettingName",
      "categoryGroup",
      "resourceLocationList",
      "logAnalytics",
      "logAnalyticsDestinationType",
      "collectMetrics"
    ]
  },
  "processing_status": "success"
}