{
  "url": "https://www.azadvertizer.net/azpolicyadvertizer/dfe69c56-9c12-4271-9e62-7607ab669582.html",
  "timestamp": "2025-06-24T12:38:34.746871",
  "original_policy": {
    "display_name": "Enable logging by category group for Data Lake Storage Gen1 (microsoft.datalakestore/accounts) to Log Analytics",
    "policy_type": "BuiltIn",
    "had_category_group": true,
    "original_parameters": [
      "effect",
      "diagnosticSettingName",
      "categoryGroup",
      "resourceLocationList",
      "logAnalytics",
      "logAnalyticsDestinationType",
      "collectMetrics"
    ]
  },
  "modified_policy": {
    "service_name_extracted": "Data Lake Storage Gen1",
    "filename_generated": "Data Lake Storage Gen1 - custom.json",
    "final_parameters": [
      "effect",
      "diagnosticSettingName",
      "categoryGroup",
      "resourceLocationList",
      "logAnalytics",
      "logAnalyticsDestinationType",
      "collectMetrics"
    ]
  },
  "processing_status": "success"
}