{
  "url": "https://www.azadvertizer.net/azpolicyadvertizer/8fc4ca5f-6abc-4b30-9565-0bd91ac49420.html",
  "timestamp": "2025-06-24T12:38:48.114728",
  "original_policy": {
    "display_name": "Enable logging by category group for SQL managed instances (microsoft.sql/managedinstances) to Log Analytics",
    "policy_type": "BuiltIn",
    "had_category_group": true,
    "original_parameters": [
      "effect",
      "diagnosticSettingName",
      "categoryGroup",
      "resourceLocationList",
      "logAnalytics",
      "logAnalyticsDestinationType",
      "collectMetrics"
    ]
  },
  "modified_policy": {
    "service_name_extracted": "SQL managed instances",
    "filename_generated": "SQL managed instances - custom.json",
    "final_parameters": [
      "effect",
      "diagnosticSettingName",
      "categoryGroup",
      "resourceLocationList",
      "logAnalytics",
      "logAnalyticsDestinationType",
      "collectMetrics"
    ]
  },
  "processing_status": "success"
}